tool_yy/__about__.py
tool_yy/__init__.py
tool_yy/config/__init__.py
tool_yy/config/dbconfig.py
tool_yy/config/phoenix_db_config.py
tool_yy/config/settings.py
tool_yy/lib/__init__.py
tool_yy/lib/_compat.py
tool_yy/lib/config.py
tool_yy/lib/db.py
tool_yy/lib/function.py
tool_yy/lib/helper.py
tool_yy/lib/helper_config.py
tool_yy/lib/helper_context.py
tool_yy/lib/phoenix_db.py
tool_yy/lib/thread.py
tool_yy-0.1.15.dist-info/LICENSE
tool_yy-0.1.15.dist-info/METADATA
tool_yy-0.1.15.dist-info/WHEEL
tool_yy-0.1.15.dist-info/top_level.txt
tool_yy-0.1.15.dist-info/RECORD
