Metadata-Version: 2.1
Name: tool-yy
Version: 0.1.15
Summary: Util tools, designed by yy
Home-page: https://github.com/guaidashu/python3_tool_myself
Author: guaidashu
Author-email: song42960@gmail.com
License: MIT
Classifier: Topic :: Internet :: WWW/HTTP :: Dynamic Content
Classifier: Programming Language :: Python :: 3
Classifier: Programming Language :: Python :: 3.5
Classifier: Programming Language :: Python :: 3.5
Classifier: Programming Language :: Python :: 3.6
Classifier: Programming Language :: Python :: 3.7
License-File: LICENSE
